haskellian/asyn/promises/__init__.py
haskellian/asyn/promises/funcs.py
haskellian/asyn/promises/managed.py
haskellian/asyn/promises/ops.py
haskellian/asyn/promises/promise.py
haskellian_asyn-0.3.3.dist-info/METADATA
haskellian_asyn-0.3.3.dist-info/WHEEL
haskellian_asyn-0.3.3.dist-info/top_level.txt
haskellian_asyn-0.3.3.dist-info/RECORD
