Metadata-Version: 2.1
Name: haskellian-asyn
Version: 0.3.3
Summary: FP-style tools for async code
Author-email: Marcel Claramunt <marcel@moveread.com>
Requires-Python: >=3.10
Requires-Dist: ramda
Requires-Dist: haskellian-iterables
